pfun_cma_model/__init__.py
pfun_cma_model/api.py
pfun_cma_model/app.py
pfun_cma_model/cli.py
pfun_cma_model/data.py
pfun_cma_model/llm.py
pfun_cma_model/main.py
pfun_cma_model/stream.py
pfun_cma_model/engine/__init__.py
pfun_cma_model/engine/_setup.py
pfun_cma_model/engine/bounds.py
pfun_cma_model/engine/calc.py
pfun_cma_model/engine/calc_cext.py
pfun_cma_model/engine/calc_gpu.py
pfun_cma_model/engine/cma.py
pfun_cma_model/engine/cma_model_params.py
pfun_cma_model/engine/cma_plot.py
pfun_cma_model/engine/cma_posthoc.py
pfun_cma_model/engine/data_transfer.py
pfun_cma_model/engine/data_utils.py
pfun_cma_model/engine/fit.py
pfun_cma_model/engine/grid.py
pfun_cma_model/engine/pfun_cma_engine.c
pfun_cma_model/misc/__init__.py
pfun_cma_model/misc/decorators.py
pfun_cma_model/misc/errors.py
pfun_cma_model/misc/middleware.py
pfun_cma_model/misc/pathdefs.py
pfun_cma_model/misc/sessions.py
pfun_cma_model/misc/templating.py
pfun_cma_model/misc/types.py
pfun_cma_model/routes/__init__.py
pfun_cma_model/routes/data.py
pfun_cma_model/routes/demo.py
pfun_cma_model/routes/dexcom.py
pfun_cma_model/routes/llm.py
pfun_cma_model/routes/params.py
pfun_cma_model/routes/ws.py
pfun_cma_model/sso/__init__.py
pfun_cma_model/sso/sso.py
pfun_cma_model/static/style.css
pfun_cma_model/static/canvas-wave-demo/canvas-wave-demo.css
pfun_cma_model/static/canvas-wave-demo/canvas-wave-demo.js
pfun_cma_model/static/data-stream-demo/data-stream-demo.css
pfun_cma_model/static/data-stream-demo/data-stream-demo.js
pfun_cma_model/static/dexcom/app.js
pfun_cma_model/static/dexcom/dexcom-api-technical-spec.md
pfun_cma_model/static/dexcom/dexcom-cgm-dashboard.zip.zip
pfun_cma_model/static/dexcom/dexcom-extension-guide.md
pfun_cma_model/static/dexcom/style.css
pfun_cma_model/static/fluid-demo/fluid-demo.js
pfun_cma_model/static/full-model-run/full-model-run.js
pfun_cma_model/static/icons/pfun-cutielogo-icon.ico
pfun_cma_model/static/icons/pfun-cutielogo-icon.png
pfun_cma_model/static/images/pfun-cross-logo.png
pfun_cma_model-0.4.149.dist-info/METADATA
pfun_cma_model-0.4.149.dist-info/WHEEL
pfun_cma_model-0.4.149.dist-info/entry_points.txt
pfun_cma_model-0.4.149.dist-info/RECORD
