Metadata-Version: 2.4
Name: pfun-cma-model
Version: 0.4.149
Summary: A Python package for the Physiofunctional CMA model, a generative model that functionally replicates neuroendocrine dynamics.
Project-URL: homepage, https://github.com/rocapp/pfun-cma-model
Author-email: Robbie Capps <robbie@pfun.me>
Requires-Python: <3.12.13,>=3.12.11
Requires-Dist: aioredis>=2.0.1
Requires-Dist: click>=8.1.7
Requires-Dist: dotenv>=0.9.9
Requires-Dist: duckdb>=1.4.3
Requires-Dist: fastapi-sso>=0.19.0
Requires-Dist: fastapi[standard]==0.116.1
Requires-Dist: graphql-core>=3.2.3
Requires-Dist: gunicorn>=23.0.0
Requires-Dist: ipykernel>=6.29.5
Requires-Dist: itsdangerous>=2.2.0
Requires-Dist: jinja2>=3.1.2
Requires-Dist: matplotlib>=3.8.0
Requires-Dist: mss>=10.1.0
Requires-Dist: numba>=0.63.1
Requires-Dist: numpy>=2.2.6
Requires-Dist: pandas>=2.1.1
Requires-Dist: pfun-common
Requires-Dist: pfun-path-helper>=0.1.4
Requires-Dist: pip>=25.1.1
Requires-Dist: pyarrow>=20.0.0
Requires-Dist: pydantic-settings>=2.2.1
Requires-Dist: python-socketio-stubs>=5.13.0.12.20250809
Requires-Dist: python-socketio>=5.13.0
Requires-Dist: pyyaml>=6.0.1
Requires-Dist: redis>=6.4.0
Requires-Dist: requests>=2.32.4
Requires-Dist: scikit-learn>=1.3.2
Requires-Dist: scipy>=1.11.3
Requires-Dist: seaborn>=0.13.2
Requires-Dist: setuptools>=78.1.1
Requires-Dist: tabulate>=0.9.0
Requires-Dist: websockets<15.0,>=13.0
Provides-Extra: cext
Provides-Extra: dev
Requires-Dist: dotenv>=0.9.9; extra == 'dev'
Requires-Dist: fastapi[standard]>=0.115.12; extra == 'dev'
Requires-Dist: ipykernel>=6.29.5; extra == 'dev'
Requires-Dist: ipython>=8.37.0; extra == 'dev'
Requires-Dist: mypy>=1.18.1; extra == 'dev'
Requires-Dist: nbconvert>=7.16.6; extra == 'dev'
Requires-Dist: openapi-generator-cli[jdk4py]>=7.17.0; extra == 'dev'
Requires-Dist: pandas-stubs>=2.2.3.250527; extra == 'dev'
Requires-Dist: pytest-asyncio>=1.3.0; extra == 'dev'
Requires-Dist: pytest>=9.0.2; extra == 'dev'
Requires-Dist: python-package-size>=1.0.1; extra == 'dev'
Requires-Dist: types-requests>=2.32.4.20250611; extra == 'dev'
Requires-Dist: types-setuptools>=80.9.0.20251223; extra == 'dev'
Requires-Dist: types-tabulate>=0.9.0.20241207; extra == 'dev'
Provides-Extra: numba
Requires-Dist: numba>=0.58.0; extra == 'numba'
Provides-Extra: ui
